LICENSE
README.md
setup.py
damsenviet/__init__.py
damsenviet.kle.egg-info/PKG-INFO
damsenviet.kle.egg-info/SOURCES.txt
damsenviet.kle.egg-info/dependency_links.txt
damsenviet.kle.egg-info/namespace_packages.txt
damsenviet.kle.egg-info/requires.txt
damsenviet.kle.egg-info/top_level.txt
damsenviet/kle/__init__.py
damsenviet/kle/background.py
damsenviet/kle/key.py
damsenviet/kle/keyboard.py
damsenviet/kle/label.py
damsenviet/kle/metadata.py
damsenviet/kle/switch.py
damsenviet/kle/utils.py