Metadata-Version: 2.1
Name: damsenviet.kle
Version: 1.0.1
Summary: A Python library for interacting with KLE data structures and files.
Home-page: https://github.com/DamSenViet/kle-py
Author: DamSenViet
License: MIT
Project-URL: Source, https://github.com/DamSenViet/kle-py
Project-URL: Documentation, https://damsenviet.github.io/kle-py/
Keywords: keyboard layout editor serial
Platform: UNKNOWN
Classifier: Operating System :: OS Independent
Classifier: Programming Language :: Python :: 3.7
Classifier: Programming Language :: Python :: 3.8
Classifier: Programming Language :: Python :: 3.9
Requires-Python: >=3.7
Provides-Extra: dev
